topicgpt/Clustering.py
topicgpt/ExtractTopWords.py
topicgpt/GetEmbeddingsOpenAI.py
topicgpt/TopicGPT.py
topicgpt/TopicPrompting.py
topicgpt/TopicRepresentation.py
topicgpt/TopwordEnhancement.py
topicgpt/__init__.py
topicgpt-1.0.0.dist-info/METADATA
topicgpt-1.0.0.dist-info/WHEEL
topicgpt-1.0.0.dist-info/top_level.txt
topicgpt-1.0.0.dist-info/RECORD
